{
  "tenantId": "hp.Dalhousie",
  "moduleName": "TradeLicense",
  "FeeStructure": [
    {
      "tenantId": "hp.Dalhousie",
      "feeStructureOf": "scaleOfBusiness",
      "type": "Small",
      "price": 1500,
      "periodOfLicense": 1
    },
    {
      "tenantId": "hp.Dalhousie",
      "feeStructureOf": "scaleOfBusiness",
      "type": "Small",
      "price": 6000,
      "periodOfLicense": 5
    },
    {
      "tenantId": "hp.Dalhousie",
      "feeStructureOf": "scaleOfBusiness",
      "type": "Small",
      "price": 12000,
      "periodOfLicense": 10
    },
    {
      "tenantId": "hp.Dalhousie",
      "feeStructureOf": "scaleOfBusiness",
      "type": "Small",
      "price": 18000,
      "periodOfLicense": 15
    },
    {
      "tenantId": "hp.Dalhousie",
      "feeStructureOf": "scaleOfBusiness",
      "type": "Medium",
      "price": 2500,
      "periodOfLicense": 1
    },
    {
      "tenantId": "hp.Dalhousie",
      "feeStructureOf": "scaleOfBusiness",
      "type": "Medium",
      "price": 10000,
      "periodOfLicense": 5
    },
    {
      "tenantId": "hp.Dalhousie",
      "feeStructureOf": "scaleOfBusiness",
      "type": "Medium",
      "price": 20000,
      "periodOfLicense": 10
    },
    {
      "tenantId": "hp.Dalhousie",
      "feeStructureOf": "scaleOfBusiness",
      "type": "Medium",
      "price": 30000,
      "periodOfLicense": 15
    },
    {
      "tenantId": "hp.Dalhousie",
      "feeStructureOf": "scaleOfBusiness",
      "type": "Large",
      "price": 4000,
      "periodOfLicense": 1
    },
    {
      "tenantId": "hp.Dalhousie",
      "feeStructureOf": "scaleOfBusiness",
      "type": "Large",
      "price": 16000,
      "periodOfLicense": 5
    },
    {
      "tenantId": "hp.Dalhousie",
      "feeStructureOf": "scaleOfBusiness",
      "type": "Large",
      "price": 32000,
      "periodOfLicense": 10
    },
    {
      "tenantId": "hp.Dalhousie",
      "feeStructureOf": "scaleOfBusiness",
      "type": "Large",
      "price": 48000,
      "periodOfLicense": 15
    },
    {
      "tenantId": "hp.Dalhousie",
      "feeStructureOf": "tradeCategory",
      "type": "Agriculture",
      "price": 1500
    },
    {
      "tenantId": "hp.Dalhousie",
      "feeStructureOf": "tradeCategory",
      "type": "Automotive",
      "price": 5000
    },
    {
      "tenantId": "hp.Dalhousie",
      "feeStructureOf": "tradeCategory",
      "type": "Banking Finance Services Insurance (BFSI)",
      "price": 5000
    },
    {
      "tenantId": "hp.Dalhousie",
      "feeStructureOf": "tradeCategory",
      "type": "Common Trades",
      "price": 1500
    },
    {
      "tenantId": "hp.Dalhousie",
      "feeStructureOf": "tradeCategory",
      "type": "Education, Skills & Development",
      "price": 5000
    },
    {
      "tenantId": "hp.Dalhousie",
      "feeStructureOf": "tradeCategory",
      "type": "Fairs, Festivals, Events, and Exhibitions (Temporary Licenses Only)",
      "price": 1000
    },
    {
      "tenantId": "hp.Dalhousie",
      "feeStructureOf": "tradeCategory",
      "type": "Handloom & Handicrafts",
      "price": 1000
    },
    {
      "tenantId": "hp.Dalhousie",
      "feeStructureOf": "tradeCategory",
      "type": "IT/ ITES Services",
      "price": 5000
    },
    {
      "tenantId": "hp.Dalhousie",
      "feeStructureOf": "tradeCategory",
      "type": "Luxury Goods",
      "price": 5000
    },
    {
      "tenantId": "hp.Dalhousie",
      "feeStructureOf": "tradeCategory",
      "type": "Manufacturing, Industries and Industrial Materials",
      "price": 4000
    },
    {
      "tenantId": "hp.Dalhousie",
      "feeStructureOf": "tradeCategory",
      "type": "Petroleum, Chemicals & Other Regulated Products",
      "price": 5000
    },
    {
      "tenantId": "hp.Dalhousie",
      "feeStructureOf": "tradeCategory",
      "type": "Tourism & Hospitality",
      "price": 5000
    },
    {
      "tenantId": "hp.Dalhousie",
      "feeStructureOf": "tradeCategory",
      "type": "Transportation & Logistics",
      "price": 5000
    }
  ]
}
